codefield/__init__.py
codefield/__main__.py
codefield/pyrustic_data/backstage/config/build.json
codefield/pyrustic_data/backstage/config/init.json
codefield/pyrustic_data/backstage/config/release.json
codefield/pyrustic_data/backstage/data/github_release_form.json
codefield/pyrustic_data/backstage/report/build_report.json
codefield/pyrustic_data/backstage/report/release_report.json
codefield/pyrustic_data/hubstore/img.json
codefield/pyrustic_data/hubstore/promotion.json
tests/__init__.py
codefield-0.0.1.dist-info/LICENSE
codefield-0.0.1.dist-info/METADATA
codefield-0.0.1.dist-info/WHEEL
codefield-0.0.1.dist-info/entry_points.txt
codefield-0.0.1.dist-info/top_level.txt
codefield-0.0.1.dist-info/RECORD
